internetspeedtest/__init__.py
internetspeedtest/__main__.py
internetspeedtest/cli.py
internetspeedtest/progress.py
internetspeedtest/speedtest.py
internetspeedtest-1.0.1.dist-info/licenses/LICENSE
internetspeedtest-1.0.1.dist-info/METADATA
internetspeedtest-1.0.1.dist-info/WHEEL
internetspeedtest-1.0.1.dist-info/entry_points.txt
internetspeedtest-1.0.1.dist-info/top_level.txt
internetspeedtest-1.0.1.dist-info/RECORD
