Metadata-Version: 2.4
Name: internetspeedtest
Version: 1.0.1
Summary: InternetSpeedTest command line interface - Python implementation
Home-page: https://github.com/internetspeedtest-net/internetspeedtest-py
Author: LibreSpeed
Author-email: 
License: LGPL-3.0
Project-URL: Homepage, https://github.com/internetspeedtest-net/internetspeedtest-py
Project-URL: Documentation, https://github.com/internetspeedtest-net/internetspeedtest-py/tree/master/python
Project-URL: Repository, https://github.com/internetspeedtest-net/internetspeedtest-py
Project-URL: Issues, https://github.com/internetspeedtest-net/internetspeedtest-py/issues
Keywords: speedtest,internetspeedtest,internet,speed,cli,network
Classifier: Development Status :: 4 - Beta
Classifier: Intended Audience :: Developers
Classifier: Intended Audience :: System Administrators
Classifier: License :: OSI Approved :: GNU Lesser General Public License v3 (LGPLv3)
Classifier: Operating System :: OS Independent
Classifier: Programming Language :: Python :: 3
Classifier: Programming Language :: Python :: 3.7
Classifier: Programming Language :: Python :: 3.8
Classifier: Programming Language :: Python :: 3.9
Classifier: Programming Language :: Python :: 3.10
Classifier: Programming Language :: Python :: 3.11
Classifier: Programming Language :: Python :: 3.12
Classifier: Topic :: Internet
Classifier: Topic :: System :: Networking
Classifier: Topic :: Utilities
Requires-Python: >=3.7
License-File: LICENSE
Requires-Dist: requests>=2.25.0
Dynamic: home-page
Dynamic: license-file
Dynamic: requires-python
